pytestshellutils/__init__.py
pytestshellutils/customtypes.py
pytestshellutils/exceptions.py
pytestshellutils/plugin.py
pytestshellutils/py.typed
pytestshellutils/shell.py
pytestshellutils/version.py
pytestshellutils/utils/__init__.py
pytestshellutils/utils/ports.py
pytestshellutils/utils/processes.py
pytestshellutils/utils/socket.py
pytestshellutils/utils/socket.pyi
pytestshellutils/utils/time.py
pytestshellutils/utils/time.pyi
pytest_shell_utilities-1.9.7.dist-info/LICENSE
pytest_shell_utilities-1.9.7.dist-info/METADATA
pytest_shell_utilities-1.9.7.dist-info/WHEEL
pytest_shell_utilities-1.9.7.dist-info/entry_points.txt
pytest_shell_utilities-1.9.7.dist-info/top_level.txt
pytest_shell_utilities-1.9.7.dist-info/RECORD
