Metadata-Version: 2.1
Name: pytest-shell-utilities
Version: 1.9.7
Summary: Pytest plugin to simplify running shell commands against the system
Home-page: https://github.com/saltstack/pytest-shell-utilities
Author: Pedro Algarvio
Author-email: pedro@algarvio.me
License: Apache Software License 2.0
Project-URL: Source, https://github.com/saltstack/pytest-shell-utilities
Project-URL: Tracker, https://github.com/saltstack/pytest-shell-utilities/issues
Project-URL: Documentation, https://pytest-shell-utilities.readthedocs.io
Platform: unix
Platform: linux
Platform: osx
Platform: cygwin
Platform: win32
Classifier: Programming Language :: Python
Classifier: Programming Language :: Cython
Classifier: Programming Language :: Python :: 3
Classifier: Programming Language :: Python :: 3 :: Only
Classifier: Programming Language :: Python :: 3.8
Classifier: Programming Language :: Python :: 3.9
Classifier: Programming Language :: Python :: 3.10
Classifier: Programming Language :: Python :: 3.11
Classifier: Typing :: Typed
Classifier: Development Status :: 5 - Production/Stable
Classifier: Intended Audience :: Developers
Classifier: License :: OSI Approved :: Apache Software License
Requires-Python: >=3.8
License-File: LICENSE
Requires-Dist: pytest >=7.4.0
Requires-Dist: attrs >=22.1.0
Requires-Dist: psutil >=5.0.0
Requires-Dist: pytest-helpers-namespace
Requires-Dist: pytest-skip-markers
Provides-Extra: changelog
Requires-Dist: towncrier ==21.9.0rc1 ; extra == 'changelog'
Provides-Extra: docs
Requires-Dist: towncrier <=23.11.0 ; extra == 'docs'
Requires-Dist: furo ; extra == 'docs'
Requires-Dist: sphinx ; extra == 'docs'
Requires-Dist: sphinx-copybutton ; extra == 'docs'
Requires-Dist: sphinx-prompt ; extra == 'docs'
Requires-Dist: sphinxcontrib-spelling ; extra == 'docs'
Requires-Dist: sphinxcontrib-towncrier >=0.2.1a0 ; extra == 'docs'
Provides-Extra: lint
Requires-Dist: pylint ==2.12.2 ; extra == 'lint'
Requires-Dist: pyenchant ; extra == 'lint'
Requires-Dist: flake8 >=4.0.1 ; extra == 'lint'
Requires-Dist: flake8-mypy-fork ; extra == 'lint'
Requires-Dist: flake8-docstrings ; extra == 'lint'
Requires-Dist: flake8-typing-imports ; extra == 'lint'
Requires-Dist: black ; (python_version >= "3.7") and extra == 'lint'
Requires-Dist: reorder-python-imports ; (python_version >= "3.7") and extra == 'lint'
Provides-Extra: tests
Requires-Dist: pytest-subtests ; extra == 'tests'
Requires-Dist: pytest-skip-markers ; extra == 'tests'
